ncaars/__init__.py
ncaars-0.0.0.dist-info/entry_points.txt
ncaars-0.0.0.dist-info/LICENSE.txt
ncaars-0.0.0.dist-info/WHEEL
ncaars-0.0.0.dist-info/METADATA
ncaars-0.0.0.dist-info/RECORD
