Metadata-Version: 2.1
Name: ncaars
Version: 0.0.0
Summary: Expand the genetic code: design aaRSs for NCAAs
Home-page: https://github.com/kalekundert/ncaars
License: UNKNOWN
Author: Kale Kundert
Author-email: kale@thekunderts.net
Requires-Python: ~=3.9
Classifier: Programming Language :: Python :: 3
Classifier: License :: OSI Approved :: GNU General Public License v3 (GPLv3)
Requires-Dist: sphinx ; extra == "doc"
Requires-Dist: sphinx_rtd_theme ; extra == "doc"
Requires-Dist: autoclasstoc ; extra == "doc"
Requires-Dist: pytest ; extra == "test"
Requires-Dist: pytest-cov ; extra == "test"
Requires-Dist: parametrize_from_file ; extra == "test"
Requires-Dist: coveralls ; extra == "test"
Project-URL: Bug Tracker, https://github.com/kalekundert/ncaars/issues
Project-URL: Continuous Integration, https://github.com/kalekundert/ncaars/actions
Project-URL: Documentation, https://ncaars.readthedocs.io/en/latest/
Project-URL: Test Coverage, https://coveralls.io/github/kalekundert/ncaars
Project-URL: Version Control, https://github.com/kalekundert/ncaars
Provides-Extra: doc
Provides-Extra: test
